roughness_calculator/__init__.py
roughness_calculator/cli_main.py
roughness_calculator/gui_main.py
roughness_calculator/log_config.py
roughness_calculator/main.py
roughness_calculator/classes/__init__.py
roughness_calculator/classes/application_driver.py
roughness_calculator/classes/defaults.py
roughness_calculator/classes/geo_tiff_processor.py
roughness_calculator/classes/processing_parameters.py
roughness_calculator/classes/threshold_optimizer.py
roughness_calculator/gui/__init__.py
roughness_calculator/gui/analyze_and_optimize.py
roughness_calculator/gui/defaults.py
roughness_calculator/gui/encapsulating_frame.py
roughness_calculator/gui/footer_frame.py
roughness_calculator/gui/header_frame.py
roughness_calculator/gui/parameter_input.py
roughness_calculator/gui/path_frame.py
roughness_calculator/gui/preview_image.py
roughness_calculator/old_entry_points/__init__.py
roughness_calculator/old_entry_points/demcli.py
roughness_calculator/old_entry_points/demgui.py
tests/__init__.py
tests/test_application_driver.py
dem_roughness_calculator-1.3.0.dist-info/LICENSE
dem_roughness_calculator-1.3.0.dist-info/METADATA
dem_roughness_calculator-1.3.0.dist-info/WHEEL
dem_roughness_calculator-1.3.0.dist-info/entry_points.txt
dem_roughness_calculator-1.3.0.dist-info/top_level.txt
dem_roughness_calculator-1.3.0.dist-info/RECORD
