Metadata-Version: 2.1
Name: dem-roughness-calculator
Version: 1.3.0
Summary: A package for calculating surface roughness using GeoTIFF DEM files with a GUI and CLI
Home-page: https://github.com/lbatschelet/dem-roughness-calculator
Author: lbatschelet
License: GPL-3.0
Classifier: Development Status :: 4 - Beta
Classifier: Intended Audience :: Science/Research
Classifier: License :: OSI Approved :: GNU General Public License v3 (GPLv3)
Classifier: Operating System :: OS Independent
Classifier: Programming Language :: Python :: 3
Classifier: Programming Language :: Python :: 3.12
Classifier: Topic :: Scientific/Engineering :: GIS
Requires-Python: >=3.12
License-File: LICENSE
Requires-Dist: matplotlib >=3.8.4
Requires-Dist: numpy >=1.26.4
Requires-Dist: pillow >=10.3.0
Requires-Dist: rasterio >=1.3.10
Requires-Dist: setuptools >=69.5.1
Requires-Dist: customtkinter ~=5.2.2
Requires-Dist: scipy ~=1.13.0
